morecontext/__init__.py
morecontext/py.typed
morecontext-0.6.1.dist-info/METADATA
morecontext-0.6.1.dist-info/WHEEL
morecontext-0.6.1.dist-info/licenses/LICENSE
morecontext-0.6.1.dist-info/RECORD
