Metadata-Version: 2.3
Name: morecontext
Version: 0.6.1
Summary: Context managers for changing directory, setting attributes/envvars, etc.
Project-URL: Source Code, https://github.com/jwodder/morecontext
Project-URL: Bug Tracker, https://github.com/jwodder/morecontext/issues
Author-email: John Thorvald Wodder II <morecontext@varonathe.org>
License: MIT
Keywords: chdir,context managers,environ,envvar,monkeypatch,setenv,with
Classifier: Intended Audience :: Developers
Classifier: License :: OSI Approved :: MIT License
Classifier: Programming Language :: Python :: 3
Classifier: Programming Language :: Python :: 3 :: Only
Classifier: Programming Language :: Python :: 3.8
Classifier: Programming Language :: Python :: 3.9
Classifier: Programming Language :: Python :: 3.10
Classifier: Programming Language :: Python :: 3.11
Classifier: Programming Language :: Python :: 3.12
Classifier: Programming Language :: Python :: 3.13
Classifier: Programming Language :: Python :: Implementation :: CPython
Classifier: Programming Language :: Python :: Implementation :: PyPy
Classifier: Topic :: Utilities
Classifier: Typing :: Typed
Requires-Python: >=3.8
